ohmyapi/__init__.py
ohmyapi/__main__.py
ohmyapi/builtin/auth/__init__.py
ohmyapi/builtin/auth/models.py
ohmyapi/builtin/auth/permissions.py
ohmyapi/builtin/auth/routes.py
ohmyapi/builtin/auth/utils.py
ohmyapi/builtin/demo/__init__.py
ohmyapi/builtin/demo/models.py
ohmyapi/builtin/demo/routes.py
ohmyapi/cli.py
ohmyapi/core/__init__.py
ohmyapi/core/logging.py
ohmyapi/core/runtime.py
ohmyapi/core/scaffolding.py
ohmyapi/core/templates/app/__init__.py.j2
ohmyapi/core/templates/app/models.py.j2
ohmyapi/core/templates/app/routes.py.j2
ohmyapi/core/templates/docker/Dockerfile
ohmyapi/core/templates/docker/docker-compose.yml
ohmyapi/core/templates/project/README.md.j2
ohmyapi/core/templates/project/pyproject.toml.j2
ohmyapi/core/templates/project/settings.py.j2
ohmyapi/db/__init__.py
ohmyapi/db/exceptions.py
ohmyapi/db/functions.py
ohmyapi/db/model/__init__.py
ohmyapi/db/model/model.py
ohmyapi/middleware/cors.py
ohmyapi/router.py
ohmyapi-0.6.2.dist-info/METADATA
ohmyapi-0.6.2.dist-info/WHEEL
ohmyapi-0.6.2.dist-info/entry_points.txt
ohmyapi-0.6.2.dist-info/RECORD
