Metadata-Version: 2.4
Name: ohmyapi
Version: 0.6.2
Summary: Django-flavored scaffolding and management layer around FastAPI, Pydantic, TortoiseORM and Aerich migrations
License-Expression: MIT
Keywords: fastapi,tortoise,orm,pydantic,async,web-framework
Author: Brian Wiborg
Author-email: me@brianwib.org
Requires-Python: >=3.11
Classifier: Programming Language :: Python :: 3
Classifier: Programming Language :: Python :: 3.11
Classifier: Programming Language :: Python :: 3.12
Classifier: Programming Language :: Python :: 3.13
Classifier: Programming Language :: Python :: 3.14
Provides-Extra: auth
Requires-Dist: aerich (>=0.9.1,<0.10.0)
Requires-Dist: argon2-cffi (>=25.1.0,<26.0.0)
Requires-Dist: argon2-cffi ; extra == "auth"
Requires-Dist: crypto (>=1.4.1,<2.0.0)
Requires-Dist: crypto ; extra == "auth"
Requires-Dist: fastapi (>=0.117.1,<0.118.0)
Requires-Dist: ipython (>=9.5.0,<10.0.0)
Requires-Dist: jinja2 (>=3.1.6,<4.0.0)
Requires-Dist: passlib (>=1.7.4,<2.0.0)
Requires-Dist: passlib ; extra == "auth"
Requires-Dist: pyjwt (>=2.10.1,<3.0.0)
Requires-Dist: pyjwt ; extra == "auth"
Requires-Dist: python-multipart (>=0.0.20,<0.0.21)
Requires-Dist: python-multipart ; extra == "auth"
Requires-Dist: tortoise-orm (>=0.25.1,<0.26.0)
Requires-Dist: typer (>=0.19.1,<0.20.0)
Requires-Dist: uvicorn (>=0.36.0,<0.37.0)
Project-URL: Repository, https://code.c-base.org/baccenfutter/ohmyapi
